fync/__init__.py
fync/fync.py
fync/get.py
fync-1.3.1.dist-info/LICENSE
fync-1.3.1.dist-info/METADATA
fync-1.3.1.dist-info/WHEEL
fync-1.3.1.dist-info/entry_points.txt
fync-1.3.1.dist-info/RECORD
