Metadata-Version: 2.3
Name: fync
Version: 1.3.1
Summary: Automatically trigger command on directory update
License: MIT
Author: Fanuware
Author-email: fanuware@gmail.com
Requires-Python: >=3.9,<4.0
Classifier: License :: OSI Approved :: MIT License
Classifier: Programming Language :: Python :: 3
Classifier: Programming Language :: Python :: 3.9
Classifier: Programming Language :: Python :: 3.10
Classifier: Programming Language :: Python :: 3.11
Classifier: Programming Language :: Python :: 3.12
Classifier: Programming Language :: Python :: 3.13
Requires-Dist: watchdog (>=6.0.0,<7.0.0)
